metaflow-stubs/__init__.pyi
metaflow-stubs/cards.pyi
metaflow-stubs/cli.pyi
metaflow-stubs/events.pyi
metaflow-stubs/exception.pyi
metaflow-stubs/flowspec.pyi
metaflow-stubs/generated_for.txt
metaflow-stubs/includefile.pyi
metaflow-stubs/meta_files.pyi
metaflow-stubs/metaflow_config.pyi
metaflow-stubs/metaflow_current.pyi
metaflow-stubs/metaflow_git.pyi
metaflow-stubs/multicore_utils.pyi
metaflow-stubs/ob_internal.pyi
metaflow-stubs/parameters.pyi
metaflow-stubs/py.typed
metaflow-stubs/pylint_wrapper.pyi
metaflow-stubs/tagging_util.pyi
metaflow-stubs/tuple_util.pyi
metaflow-stubs/cli_components/__init__.pyi
metaflow-stubs/cli_components/utils.pyi
metaflow-stubs/client/__init__.pyi
metaflow-stubs/client/core.pyi
metaflow-stubs/client/filecache.pyi
metaflow-stubs/metadata_provider/__init__.pyi
metaflow-stubs/metadata_provider/heartbeat.pyi
metaflow-stubs/metadata_provider/metadata.pyi
metaflow-stubs/metadata_provider/util.pyi
metaflow-stubs/mf_extensions/__init__.pyi
metaflow-stubs/mf_extensions/obcheckpoint/__init__.pyi
metaflow-stubs/mf_extensions/obcheckpoint/plugins/__init__.pyi
metaflow-stubs/mf_extensions/obcheckpoint/plugins/machine_learning_utilities/__init__.pyi
metaflow-stubs/mf_extensions/obcheckpoint/plugins/machine_learning_utilities/datastructures.pyi
metaflow-stubs/mf_extensions/obcheckpoint/plugins/machine_learning_utilities/exceptions.pyi
metaflow-stubs/mf_extensions/obcheckpoint/plugins/machine_learning_utilities/card_utils/__init__.pyi
metaflow-stubs/mf_extensions/obcheckpoint/plugins/machine_learning_utilities/card_utils/async_cards.pyi
metaflow-stubs/mf_extensions/obcheckpoint/plugins/machine_learning_utilities/card_utils/deco_injection_mixin.pyi
metaflow-stubs/mf_extensions/obcheckpoint/plugins/machine_learning_utilities/card_utils/extra_components.pyi
metaflow-stubs/mf_extensions/obcheckpoint/plugins/machine_learning_utilities/checkpoints/__init__.pyi
ob_metaflow_stubs-6.0.11.2.dist-info/METADATA
ob_metaflow_stubs-6.0.11.2.dist-info/WHEEL
ob_metaflow_stubs-6.0.11.2.dist-info/top_level.txt
ob_metaflow_stubs-6.0.11.2.dist-info/RECORD
