Metadata-Version: 2.4
Name: ob-metaflow-stubs
Version: 6.0.11.2
Summary: Metaflow Stubs: Stubs for the metaflow package
Author: Netflix, Outerbounds & the Metaflow Community
Author-email: help@outerbounds.co
License: Apache License 2.0
Requires-Python: >=3.7.0
Dynamic: author
Dynamic: author-email
Dynamic: description
Dynamic: description-content-type
Dynamic: license
Dynamic: requires-python
Dynamic: summary
